LICENSE
setup.py
elay_help.egg-info/PKG-INFO
elay_help.egg-info/SOURCES.txt
elay_help.egg-info/dependency_links.txt
elay_help.egg-info/top_level.txt
elayhelp/__init__.py