Metadata-Version: 2.1
Name: elay-help
Version: 1.0.0.1
Summary: Un par de funciones pa facilitarme la via mami ya tu sae
Author: ElayPY
License: MIT
License-File: LICENSE
